ppkt2synergy/__init__.py
ppkt2synergy/analysis/__init__.py
ppkt2synergy/analysis/correlation_type.py
ppkt2synergy/analysis/hpo_correlation_analyzer.py
ppkt2synergy/analysis/pairwise_synergy_analyzer.py
ppkt2synergy/io/__init__.py
ppkt2synergy/io/cohort_loader.py
ppkt2synergy/io/hpo_loader.py
ppkt2synergy/preprocessing/__init__.py
ppkt2synergy/preprocessing/_utils.py
ppkt2synergy/preprocessing/phenopacket_matrix_generator.py
ppkt2synergy/preprocessing/phenopacket_matrix_processor.py
ppkt2synergy/synergy_tree/__init__.py
ppkt2synergy/synergy_tree/builder.py
ppkt2synergy/synergy_tree/mi_calculator.py
ppkt2synergy/synergy_tree/partition.py
ppkt2synergy/synergy_tree/tree_node.py
ppkt2synergy/synergy_tree/visualizer.py
ppkt2synergy-0.0.7.dist-info/licenses/LICENSE
ppkt2synergy-0.0.7.dist-info/METADATA
ppkt2synergy-0.0.7.dist-info/WHEEL
ppkt2synergy-0.0.7.dist-info/top_level.txt
ppkt2synergy-0.0.7.dist-info/RECORD
