Metadata-Version: 2.4
Name: ppkt2synergy
Version: 0.0.7
Summary: Search for Mutual Information and Synergy in HPO Annotations in a cohort of GA4GH phenopackets
Author-email: Peter Robinson <peter.robinson@bih-charite.de>, Daniel Danis <daniel.gordon.danis@protonmail.com>, Jing Chen <jing.chen@fu-berlin.de>
License: BSD 3-Clause License
Project-URL: homepage, https://github.com/monarch-initiative/ppkt2synergy
Project-URL: repository, https://github.com/monarch-initiative/ppkt2synergy.git
Project-URL: documentation, https://github.com/monarch-initiative/ppkt2synergy
Project-URL: bugtracker, https://github.com/monarch-initiative/ppkt2synergy/issues
Keywords: Global Alliance for Genomics and Health,GA4GH Phenopacket Schema,Human Phenotype Ontology,GA4GH,HPO
Classifier: Development Status :: 3 - Alpha
Classifier: License :: OSI Approved :: MIT License
Classifier: Operating System :: OS Independent
Classifier: Programming Language :: Python :: 3
Requires-Python: >=3.10
License-File: LICENSE
Requires-Dist: graphviz>=0.20.3
Requires-Dist: hpo-toolkit<0.6.0,>=0.5.0
Requires-Dist: matplotlib<4.0,>=3.2.0
Requires-Dist: phenopackets>=2.0.2
Requires-Dist: phenopacket-store-toolkit>=0.1.4
Requires-Dist: scikit-learn>=1.6.1
Requires-Dist: numpy<2.0.0,>=1.21.0
Requires-Dist: pandas>=1.3.0
Requires-Dist: plotly<6.0.0,>=5.5.0
Requires-Dist: nbformat<6.0.0,>=5.1.0
Requires-Dist: gpsea==0.9.8
Requires-Dist: openpyxl
Requires-Dist: scipy<2.0.0,>=1.15.0
Requires-Dist: joblib<2.0.0,>=1.3.0
Requires-Dist: tqdm<5.0.0,>=4.60.0
Requires-Dist: statsmodels<1.0.0,>=0.14.0
Provides-Extra: test
Requires-Dist: pytest<8.0.0,>=7.0.0; extra == "test"
Provides-Extra: docs
Requires-Dist: mkdocs-material[imaging]<10,>=9.5.10; extra == "docs"
Requires-Dist: mkdocs-material-extensions<2.0,>=1.3; extra == "docs"
Requires-Dist: mkdocstrings[python]<1.0,>=0.22; extra == "docs"
Requires-Dist: pillow; extra == "docs"
Requires-Dist: cairosvg; extra == "docs"
Dynamic: license-file
